treeCoreset/__init__.py
treeCoreset/client_coreset.so
treecoreset-0.1.2.data/data/LICENSE
treecoreset-0.1.2.data/data/README.md
treecoreset-0.1.2.dist-info/METADATA
treecoreset-0.1.2.dist-info/WHEEL
treecoreset-0.1.2.dist-info/top_level.txt
treecoreset-0.1.2.dist-info/RECORD
treecoreset-0.1.2.dist-info/licenses/LICENSE
