Metadata-Version: 2.4
Name: treeCoreset
Version: 0.1.2
Summary: C++ tree-based coreset library with Python bindings
Author-email: Fabrice Guibert <fabrice.guibert@epfl.ch>
License: GPL-3.0
Project-URL: Homepage, https://github.com/Shrecki/treeCoreset
Project-URL: Repository, https://github.com/Shrecki/treeCoreset.git
Classifier: Development Status :: 3 - Alpha
Classifier: Intended Audience :: Science/Research
Classifier: Programming Language :: Python :: 3.10
Classifier: Programming Language :: C++
Classifier: Topic :: Scientific/Engineering
Classifier: License :: OSI Approved :: GNU General Public License v3 (GPLv3)
Requires-Python: >=3.10
License-File: LICENSE
Requires-Dist: numpy
Dynamic: license-file
